ecoshard/__init__.py
ecoshard/__main__.py
ecoshard/ecoshard.py
ecoshard/geoprocessing/CoordFastFileIterator.h
ecoshard/geoprocessing/FastFileIterator.h
ecoshard/geoprocessing/__init__.py
ecoshard/geoprocessing/geoprocessing.py
ecoshard/geoprocessing/geoprocessing_core.cp39-win_amd64.pyd
ecoshard/geoprocessing/geoprocessing_core.pyx
ecoshard/geoprocessing/symbolic.py
ecoshard/geoprocessing/routing/LRUCache.h
ecoshard/geoprocessing/routing/__init__.py
ecoshard/geoprocessing/routing/routing.cp39-win_amd64.pyd
ecoshard/geoprocessing/routing/routing.pyx
ecoshard/geoprocessing/routing/watershed.cp39-win_amd64.pyd
ecoshard/geoprocessing/routing/watershed.cpp
ecoshard/geoprocessing/routing/watershed.pyx
ecoshard/taskgraph/Task.py
ecoshard/taskgraph/__init__.py
ecoshard-0.7.0.dist-info/LICENSE.txt
ecoshard-0.7.0.dist-info/METADATA
ecoshard-0.7.0.dist-info/WHEEL
ecoshard-0.7.0.dist-info/top_level.txt
ecoshard-0.7.0.dist-info/RECORD
