Metadata-Version: 2.1
Name: ecoshard
Version: 0.7.0
Summary: EcoShard GIS data
Home-page: https://github.com/therealspring/ecoshard
Maintainer: Rich Sharp
Maintainer-email: richpsharp@gmail.com
License: BSD
Keywords: computing reproduction
Platform: UNKNOWN
Classifier: Intended Audience :: Developers
Classifier: Natural Language :: English
Classifier: Operating System :: MacOS :: MacOS X
Classifier: Operating System :: Microsoft
Classifier: Operating System :: POSIX
Classifier: Programming Language :: Python :: 3.7
Classifier: License :: OSI Approved :: BSD License
License-File: LICENSE.txt
